ayeto/__init__.py
ayeto/_client.py
ayeto/_defaults.py
ayeto/_endpoints.py
ayeto/_exceptions.py
ayeto/_logger.py
ayeto/_utils.py
ayeto/_version.py
ayeto/requests.py
ayeto/responses.py
ayeto/types.py
ayeto/version.py
ayeto-0.0.3.dist-info/licenses/LICENSE
ayeto-0.0.3.dist-info/METADATA
ayeto-0.0.3.dist-info/WHEEL
ayeto-0.0.3.dist-info/top_level.txt
ayeto-0.0.3.dist-info/RECORD
