Metadata-Version: 2.4
Name: ayeto
Version: 0.0.3
Summary: AYETO API Client
Author-email: AYETO team <info@ayeto.ai>
License: Copyright 2025 AYETO
Project-URL: Homepage, https://ayeto.ai
Project-URL: Source, https://github.com/robodrone-dev/ayeto-python
Project-URL: Tracker, https://github.com/robodrone-dev/ayeto-python/issues
Requires-Python: >=3.8
License-File: LICENSE
Requires-Dist: pydantic>=2.11.7
Requires-Dist: requests>=2.32.4
Provides-Extra: dev
Requires-Dist: pytest>=8.4.1; extra == "dev"
Dynamic: license-file
